click_help_colors/__init__.py
click_help_colors/core.py
click_help_colors/decorators.py
click_help_colors/utils.py
click_help_colors-0.9.3.dist-info/LICENSE.txt
click_help_colors-0.9.3.dist-info/METADATA
click_help_colors-0.9.3.dist-info/WHEEL
click_help_colors-0.9.3.dist-info/top_level.txt
click_help_colors-0.9.3.dist-info/RECORD
