Metadata-Version: 2.1
Name: click-help-colors
Version: 0.9.3
Summary: Colorization of help messages in Click
Home-page: https://github.com/click-contrib/click-help-colors
License: MIT
Keywords: click
License-File: LICENSE.txt
Requires-Dist: click <9,>=7.0
Provides-Extra: dev
Requires-Dist: mypy ; extra == 'dev'
Requires-Dist: pytest ; extra == 'dev'
